{"cameraMode":{"drawMode":0,"name":"Shaded","section":"Shading Mode"},"sceneLighting":true,"audioPlay":false,"sceneViewState":{"showFog":true,"showMaterialUpdate":false,"showSkybox":true,"showFlares":true,"showImageEffects":true,"showParticleSystems":true},"in2DMode":false,"pivot":{"x":261.585205078125,"y":170.64193725585938,"z":42.03453063964844},"rotation":{"x":-0.1760886162519455,"y":0.004429548978805542,"z":-0.0007926946855150163,"w":-0.9843640327453613},"size":296.7294006347656,"orthographic":false}